{"chunk_definitions":[{"chunk_id":"csetup_chunk","chunk_label":"setup","document_id":"1A52369C","expansion_state":0,"options":{"engine":"r","include":false,"label":"setup"},"row":9,"row_count":1,"visible":true},{"chunk_id":"cz6zbeif7w1jo","chunk_label":"unnamed-chunk-1","document_id":"1A52369C","expansion_state":0,"options":{"engine":"r","label":"unnamed-chunk-2"},"row":15,"row_count":1,"visible":true},{"chunk_id":"ctrub6uoca0v6","chunk_label":"unnamed-chunk-4","document_id":"CC0CA738","expansion_state":0,"options":{"engine":"r","label":"unnamed-chunk-93"},"row":39,"row_count":1,"visible":true},{"chunk_id":"c1g3v5d08fl8e","chunk_label":"unnamed-chunk-5","document_id":"CC0CA738","expansion_state":0,"options":{"engine":"r","label":"unnamed-chunk-94"},"row":48,"row_count":1,"visible":true},{"chunk_id":"c0vf3ipm30t3w","chunk_label":"unnamed-chunk-20","document_id":"1A52369C","expansion_state":0,"options":{"engine":"r","label":"unnamed-chunk-93"},"row":236,"row_count":1,"visible":true},{"chunk_id":"cefcffer4diiq","chunk_label":"unnamed-chunk-21","document_id":"1A52369C","expansion_state":0,"options":{"engine":"r","label":"unnamed-chunk-94"},"row":311,"row_count":1,"visible":true},{"chunk_id":"cktvsicyap4mc","chunk_label":"unnamed-chunk-22","document_id":"1A52369C","expansion_state":0,"options":{"engine":"r","label":"unnamed-chunk-95"},"row":386,"row_count":1,"visible":true},{"chunk_id":"cgr41i0wl8tpk","chunk_label":"unnamed-chunk-23","document_id":"1A52369C","expansion_state":0,"options":{"engine":"r","label":"unnamed-chunk-97"},"row":461,"row_count":1,"visible":true},{"chunk_id":"ctdkm3mjvyj8y","chunk_label":"unnamed-chunk-24","document_id":"1A52369C","expansion_state":0,"options":{"engine":"r","label":"unnamed-chunk-100"},"row":536,"row_count":1,"visible":true},{"chunk_id":"cts7vp8prycle","chunk_label":"unnamed-chunk-25","document_id":"1A52369C","expansion_state":0,"options":{"engine":"r","label":"unnamed-chunk-103"},"row":611,"row_count":1,"visible":true},{"chunk_id":"cu9ij8kt47960","chunk_label":"unnamed-chunk-26","document_id":"1A52369C","expansion_state":0,"options":{"engine":"r","label":"unnamed-chunk-106"},"row":687,"row_count":1,"visible":true},{"chunk_id":"creqn54nv4kwa","chunk_label":"unnamed-chunk-27","document_id":"1A52369C","expansion_state":0,"options":{"engine":"r","label":"unnamed-chunk-108"},"row":762,"row_count":1,"visible":true},{"chunk_id":"ctzby536waqkx","chunk_label":"unnamed-chunk-28","document_id":"1A52369C","expansion_state":0,"options":{"engine":"r","label":"unnamed-chunk-111"},"row":838,"row_count":1,"visible":true},{"chunk_id":"clpd25iol8ei5","chunk_label":"unnamed-chunk-29","document_id":"1A52369C","expansion_state":0,"options":{"engine":"r","label":"unnamed-chunk-114"},"row":914,"row_count":1,"visible":true},{"chunk_id":"cjc33yp3s2qp9","chunk_label":"unnamed-chunk-30","document_id":"1A52369C","expansion_state":0,"options":{"engine":"r","label":"unnamed-chunk-116"},"row":989,"row_count":1,"visible":true},{"chunk_id":"czwrwebhqwofd","chunk_label":"unnamed-chunk-31","document_id":"1A52369C","expansion_state":0,"options":{"engine":"r","label":"unnamed-chunk-118"},"row":1065,"row_count":1,"visible":true},{"chunk_id":"cqb4mosavmcy4","chunk_label":"unnamed-chunk-32","document_id":"1A52369C","expansion_state":0,"options":{"engine":"r","label":"unnamed-chunk-120"},"row":1141,"row_count":1,"visible":true},{"chunk_id":"c3vgxn03yezu2","chunk_label":"unnamed-chunk-33","document_id":"1A52369C","expansion_state":0,"options":{"engine":"r","label":"unnamed-chunk-122"},"row":1217,"row_count":1,"visible":true},{"chunk_id":"cnpng9273to1l","chunk_label":"unnamed-chunk-34","document_id":"1A52369C","expansion_state":0,"options":{"engine":"r","label":"unnamed-chunk-124"},"row":1293,"row_count":1,"visible":true},{"chunk_id":"c1x7045vqv2cw","chunk_label":"unnamed-chunk-35","document_id":"1A52369C","expansion_state":0,"options":{"engine":"r","label":"unnamed-chunk-126"},"row":1369,"row_count":1,"visible":true},{"chunk_id":"clpf045jfo8ob","chunk_label":"unnamed-chunk-36","document_id":"1A52369C","expansion_state":0,"options":{"engine":"r","label":"unnamed-chunk-139"},"row":1375,"row_count":1,"visible":true},{"chunk_id":"cbtjfncwr6aos","chunk_label":"unnamed-chunk-37","document_id":"1A52369C","expansion_state":0,"options":{"engine":"r","label":"unnamed-chunk-137"},"row":1449,"row_count":1,"visible":true},{"chunk_id":"ck10fbie1yicd","chunk_label":"unnamed-chunk-38","document_id":"1A52369C","expansion_state":0,"options":{"engine":"r","label":"unnamed-chunk-141"},"row":1524,"row_count":1,"visible":true},{"chunk_id":"c5rbhds4ajqvf","chunk_label":"unnamed-chunk-39","document_id":"1A52369C","expansion_state":0,"options":{"engine":"r","label":"unnamed-chunk-144"},"row":1600,"row_count":1,"visible":true},{"chunk_id":"cfr5gs0g45cix","chunk_label":"unnamed-chunk-40","document_id":"1A52369C","expansion_state":0,"options":{"engine":"r","label":"unnamed-chunk-146"},"row":1675,"row_count":1,"visible":true},{"chunk_id":"cp1vmhtl3amoe","chunk_label":"unnamed-chunk-41","document_id":"1A52369C","expansion_state":0,"options":{"engine":"r","label":"unnamed-chunk-148"},"row":1751,"row_count":1,"visible":true},{"chunk_id":"cyxmtn1m9gjy9","chunk_label":"unnamed-chunk-42","document_id":"1A52369C","expansion_state":0,"options":{"engine":"r","label":"unnamed-chunk-4"},"row":1827,"row_count":1,"visible":true},{"chunk_id":"cwkoj66hslcx4","chunk_label":"unnamed-chunk-43","document_id":"CC0CA738","expansion_state":0,"options":{"engine":"r","label":"unnamed-chunk-8"},"row":1903,"row_count":1,"visible":true},{"chunk_id":"c4gtaku790gg5","chunk_label":"unnamed-chunk-44","document_id":"CC0CA738","expansion_state":0,"options":{"engine":"r","label":"unnamed-chunk-10"},"row":1978,"row_count":1,"visible":true},{"chunk_id":"c81iu10oa9786","chunk_label":"unnamed-chunk-45","document_id":"CC0CA738","expansion_state":0,"options":{"engine":"r","label":"unnamed-chunk-13"},"row":2053,"row_count":1,"visible":true},{"chunk_id":"cnfghlq4z1o7g","chunk_label":"unnamed-chunk-46","document_id":"CC0CA738","expansion_state":0,"options":{"engine":"r","label":"unnamed-chunk-17"},"row":2129,"row_count":1,"visible":true},{"chunk_id":"ce067ep7jmmcn","chunk_label":"unnamed-chunk-47","document_id":"CC0CA738","expansion_state":0,"options":{"engine":"r","label":"unnamed-chunk-20"},"row":2204,"row_count":1,"visible":true},{"chunk_id":"cjvn954o2mdq9","chunk_label":"unnamed-chunk-48","document_id":"CC0CA738","expansion_state":0,"options":{"engine":"r","label":"unnamed-chunk-22"},"row":2280,"row_count":1,"visible":true},{"chunk_id":"cm6bs9ca1mqzc","chunk_label":"unnamed-chunk-49","document_id":"CC0CA738","expansion_state":0,"options":{"engine":"r","label":"unnamed-chunk-24"},"row":2356,"row_count":1,"visible":true},{"chunk_id":"c7qlwospzypfi","chunk_label":"unnamed-chunk-50","document_id":"CC0CA738","expansion_state":0,"options":{"engine":"r","label":"unnamed-chunk-26"},"row":2432,"row_count":1,"visible":true},{"chunk_id":"ckkd0mw24da60","chunk_label":"unnamed-chunk-51","document_id":"CC0CA738","expansion_state":0,"options":{"engine":"r","label":"unnamed-chunk-28"},"row":2508,"row_count":1,"visible":true},{"chunk_id":"ct8lmgzwipet8","chunk_label":"unnamed-chunk-52","document_id":"CC0CA738","expansion_state":0,"options":{"engine":"r","label":"unnamed-chunk-31"},"row":2584,"row_count":1,"visible":true},{"chunk_id":"c6ypf6navfors","chunk_label":"unnamed-chunk-53","document_id":"CC0CA738","expansion_state":0,"options":{"engine":"r","label":"unnamed-chunk-35"},"row":2660,"row_count":1,"visible":true},{"chunk_id":"c67jb72c3o588","chunk_label":"unnamed-chunk-54","document_id":"CC0CA738","expansion_state":0,"options":{"engine":"r","label":"unnamed-chunk-37"},"row":2736,"row_count":1,"visible":true},{"chunk_id":"c90ndd84mckyi","chunk_label":"unnamed-chunk-55","document_id":"CC0CA738","expansion_state":0,"options":{"engine":"r","label":"unnamed-chunk-39"},"row":2812,"row_count":1,"visible":true},{"chunk_id":"cty0rd7u7m3e1","chunk_label":"unnamed-chunk-56","document_id":"CC0CA738","expansion_state":0,"options":{"engine":"r","label":"unnamed-chunk-42"},"row":2887,"row_count":1,"visible":true},{"chunk_id":"c7uwliq7wbvs4","chunk_label":"unnamed-chunk-57","document_id":"CC0CA738","expansion_state":0,"options":{"engine":"r","label":"unnamed-chunk-44"},"row":2963,"row_count":1,"visible":true},{"chunk_id":"c5v6f1r67yqvv","chunk_label":"unnamed-chunk-58","document_id":"CC0CA738","expansion_state":0,"options":{"engine":"r","label":"unnamed-chunk-46"},"row":3038,"row_count":1,"visible":true},{"chunk_id":"cy2ehlykz2fvj","chunk_label":"unnamed-chunk-59","document_id":"CC0CA738","expansion_state":0,"options":{"engine":"r","label":"unnamed-chunk-48"},"row":3113,"row_count":1,"visible":true},{"chunk_id":"ckurpvz2j4zto","chunk_label":"unnamed-chunk-60","document_id":"CC0CA738","expansion_state":0,"options":{"engine":"r","label":"unnamed-chunk-52"},"row":3188,"row_count":1,"visible":true},{"chunk_id":"cgjkovutyyd8c","chunk_label":"unnamed-chunk-61","document_id":"CC0CA738","expansion_state":0,"options":{"engine":"r","label":"unnamed-chunk-56"},"row":3263,"row_count":1,"visible":true},{"chunk_id":"cgheh0knd5vip","chunk_label":"unnamed-chunk-62","document_id":"CC0CA738","expansion_state":0,"options":{"engine":"r","label":"unnamed-chunk-63"},"row":3338,"row_count":1,"visible":true},{"chunk_id":"cvqpjbkvxojre","chunk_label":"unnamed-chunk-63","document_id":"CC0CA738","expansion_state":0,"options":{"engine":"r","label":"unnamed-chunk-64"},"row":3413,"row_count":1,"visible":true},{"chunk_id":"cdobwf9k1vv5p","chunk_label":"unnamed-chunk-64","document_id":"CC0CA738","expansion_state":0,"options":{"engine":"r","label":"unnamed-chunk-66"},"row":3488,"row_count":1,"visible":true},{"chunk_id":"cuxlenx7d0579","chunk_label":"unnamed-chunk-65","document_id":"CC0CA738","expansion_state":0,"options":{"engine":"r","label":"unnamed-chunk-71"},"row":3563,"row_count":1,"visible":true},{"chunk_id":"cs3vxofnm6rd2","chunk_label":"unnamed-chunk-66","document_id":"CC0CA738","expansion_state":0,"options":{"engine":"r","label":"unnamed-chunk-73"},"row":3638,"row_count":1,"visible":true},{"chunk_id":"chw3ciusxwr2u","chunk_label":"unnamed-chunk-67","document_id":"CC0CA738","expansion_state":0,"options":{"engine":"r","label":"unnamed-chunk-78"},"row":3714,"row_count":1,"visible":true},{"chunk_id":"ca7ggi3z4sz63","chunk_label":"unnamed-chunk-68","document_id":"CC0CA738","expansion_state":0,"options":{"engine":"r","label":"unnamed-chunk-84"},"row":3789,"row_count":1,"visible":true},{"chunk_id":"c2ipm439zdivn","chunk_label":"unnamed-chunk-69","document_id":"CC0CA738","expansion_state":0,"options":{"engine":"r","label":"unnamed-chunk-85"},"row":3864,"row_count":1,"visible":true},{"chunk_id":"cayr66aqcezsv","chunk_label":"unnamed-chunk-70","document_id":"CC0CA738","expansion_state":0,"options":{"engine":"r","label":"unnamed-chunk-89"},"row":3940,"row_count":1,"visible":true},{"chunk_id":"cg2tdq03x73uu","chunk_label":"unnamed-chunk-71","document_id":"CC0CA738","expansion_state":0,"options":{"engine":"r","label":"unnamed-chunk-92"},"row":4016,"row_count":1,"visible":true}],"doc_write_time":1600010073}